diplomacy_strategist/__init__.py
diplomacy_strategist/cli.py
diplomacy_strategist/diplomacy_strategist.py
diplomacy_strategist-0.1.1.dist-info/AUTHORS.rst
diplomacy_strategist-0.1.1.dist-info/LICENSE
diplomacy_strategist-0.1.1.dist-info/METADATA
diplomacy_strategist-0.1.1.dist-info/WHEEL
diplomacy_strategist-0.1.1.dist-info/entry_points.txt
diplomacy_strategist-0.1.1.dist-info/top_level.txt
diplomacy_strategist-0.1.1.dist-info/RECORD
